csv_importer/__init__.py
csv_importer/admin.py
csv_importer/apps.py
csv_importer/forms.py
csv_importer/models.py
csv_importer/tests.py
csv_importer/urls.py
csv_importer/utils.py
csv_importer/views.py
csv_importer/__pycache__/__init__.cpython-36.pyc
csv_importer/__pycache__/admin.cpython-36.pyc
csv_importer/__pycache__/forms.cpython-36.pyc
csv_importer/__pycache__/models.cpython-36.pyc
csv_importer/__pycache__/urls.cpython-36.pyc
csv_importer/__pycache__/utils.cpython-36.pyc
csv_importer/__pycache__/views.cpython-36.pyc
csv_importer/migrations/__init__.py
csv_importer/migrations/__pycache__/__init__.cpython-36.pyc
csv_importer/templates/__init__.py
csv_importer/templates/upload_csv.html
csv_importer/templates/admin/change_list.html
django_csv_import-0.3.dist-info/LICENSE
django_csv_import-0.3.dist-info/METADATA
django_csv_import-0.3.dist-info/WHEEL
django_csv_import-0.3.dist-info/top_level.txt
django_csv_import-0.3.dist-info/RECORD
